django_react_flow/__init__.py
django_react_flow/parsers/__init__.py
django_react_flow/parsers/base.py
django_react_flow/parsers/yaml.py
django_react_flow/settings.py
django_react_flow/templates/react_flow.html
django_react_flow/urls.py
django_react_flow/views/__init__.py
django_react_flow/views/react_flow.py
django_react_flow-0.1.1.dist-info/METADATA
django_react_flow-0.1.1.dist-info/WHEEL
django_react_flow-0.1.1.dist-info/RECORD
