Metadata-Version: 2.1
Name: django-react-flow
Version: 0.1.1
Summary: Building react-flow graph via django using yaml
Author: Sergei Konik
Author-email: s.konik.dev@gmail.com
Requires-Python: >=3.10,<4.0
Classifier: Programming Language :: Python :: 3
Classifier: Programming Language :: Python :: 3.10
Classifier: Programming Language :: Python :: 3.11
Requires-Dist: django (>=5.0.4,<6.0.0)
Requires-Dist: pydantic-settings (>=2.2.1,<3.0.0)
Requires-Dist: pyyaml (>=6.0.1,<7.0.0)
